[
    {
        "activity_id": 1,
        "activity_name": "Colosseum Tour",
        "location": "Rome",
        "description": "Explore the ancient Colosseum with a guided tour",
        "category": "Sightseeing",
        "rating": 4.5,
        "price": "$$",
        "duration": "2 hours",
        "availability": "Daily"
    },
    {
        "activity_id": 2,
        "activity_name": "Vatican Museums Tour",
        "location": "Rome",
        "description": "Discover the art and history of the Vatican Museums",
        "category": "Art & Culture",
        "rating": 4.8,
        "price": "$$$",
        "duration": "3 hours",
        "availability": "Daily"
    },
    {
        "activity_id": 3,
        "activity_name": "Gondola Ride",
        "location": "Venice",
        "description": "Enjoy a romantic gondola ride through Venice's canals",
        "category": "Water Tours",
        "rating": 4.2,
        "price": "$$$",
        "duration": "30 mins",
        "availability": "Daily"
    },
    {
        "activity_id": 4,
        "activity_name": "Tuscan Wine Tasting",
        "location": "Tuscany",
        "description": "Experience wine tasting in the picturesque Tuscan countryside",
        "category": "Food & Drink",
        "rating": 4.9,
        "price": "$$$$",
        "duration": "4 hours",
        "availability": "Weekends"
    },
    {
        "activity_id": 5,
        "activity_name": "Pompeii Ruins Tour",
        "location": "Pompeii",
        "description": "Explore the ancient ruins of Pompeii with a knowledgeable guide",
        "category": "History Tours",
        "rating": 4.7,
        "price": "$$$",
        "duration": "3 hours",
        "availability": "Daily"
    },
    {
        "activity_id": 6,
        "activity_name": "Uffizi Gallery Tour",
        "location": "Florence",
        "description": "Discover masterpieces of Renaissance art at the Uffizi Gallery",
        "category": "Art & Culture",
        "rating": 4.6,
        "price": "$$$",
        "duration": "2 hours",
        "availability": "Daily"
    },
    {
        "activity_id": 7,
        "activity_name": "Amalfi Coast Boat Tour",
        "location": "Amalfi Coast",
        "description": "Cruise along the stunning Amalfi Coast and visit picturesque coastal villages",
        "category": "Boat Tours",
        "rating": 4.8,
        "price": "$$$",
        "duration": "Full day",
        "availability": "Daily"
    },
    {
        "activity_id": 8,
        "activity_name": "Cinque Terre Hiking Tour",
        "location": "Cinque Terre",
        "description": "Hike through the scenic trails of the Cinque Terre National Park",
        "category": "Adventure Tours",
        "rating": 4.4,
        "price": "$$",
        "duration": "Full day",
        "availability": "Weekends"
    },
    {
        "activity_id": 9,
        "activity_name": "Venice Carnival Mask Making Workshop",
        "location": "Venice",
        "description": "Learn the art of traditional Venetian mask making from local artisans",
        "category": "Workshops",
        "rating": 4.9,
        "price": "$$$",
        "duration": "2 hours",
        "availability": "Weekdays"
    },
    {
        "activity_id": 10,
        "activity_name": "Pizza Making Class",
        "location": "Naples",
        "description": "Master the art of making authentic Neapolitan pizza with a local chef",
        "category": "Cooking Classes",
        "rating": 4.7,
        "price": "$$",
        "duration": "3 hours",
        "availability": "Daily"
    },
    {
        "activity_id": 11,
        "activity_name": "Vespa Tour of Chianti",
        "location": "Chianti",
        "description": "Explore the scenic countryside of Chianti on a vintage Vespa scooter",
        "category": "Motorbike Tours",
        "rating": 4.5,
        "price": "$$$",
        "duration": "Half day",
        "availability": "Weekends"
    },
    {
        "activity_id": 12,
        "activity_name": "Capri Island Boat Tour",
        "location": "Capri",
        "description": "Sail around the beautiful island of Capri and swim in crystal-clear waters",
        "category": "Boat Tours",
        "rating": 4.8,
        "price": "$$$",
        "duration": "Full day",
        "availability": "Daily"
    },
    {
        "activity_id": 13,
        "activity_name": "Venice Biennale Art Exhibition",
        "location": "Venice",
        "description": "Experience contemporary art at the prestigious Venice Biennale exhibition",
        "category": "Art & Culture",
        "rating": 4.6,
        "price": "$",
        "duration": "Varies",
        "availability": "Specific dates"
    },
    {
        "activity_id": 14,
        "activity_name": "Pisa Tower Climb",
        "location": "Pisa",
        "description": "Climb to the top of the iconic Leaning Tower of Pisa for panoramic views",
        "category": "Sightseeing",
        "rating": 4.3,
        "price": "$$",
        "duration": "1 hour",
        "availability": "Daily"
    },
    {
        "activity_id": 15,
        "activity_name": "Gelato Tasting Tour",
        "location": "Florence",
        "description": "Indulge in a guided tour of Florence's best gelaterias and taste delicious gelato flavors",
        "category": "Food & Drink",
        "rating": 4.9,
        "price": "$$",
        "duration": "2 hours",
        "availability": "Weekends"
    },
    {
        "activity_id": 16,
        "activity_name": "Siena Palio Horse Race",
        "location": "Siena",
        "description": "Witness the thrilling Palio horse race in the historic city of Siena",
        "category": "Events",
        "rating": 4.7,
        "price": "$",
        "duration": "1 day",
        "availability": "Specific dates"
    },
    {
        "activity_id": 17,
        "activity_name": "Vatican Gardens Tour",
        "location": "Rome",
        "description": "Explore the beautiful Vatican Gardens on a guided tour",
        "category": "Sightseeing",
        "rating": 4.6,
        "price": "$$$",
        "duration": "2 hours",
        "availability": "Weekdays"
    },
    {
        "activity_id": 18,
        "activity_name": "Truffle Hunting Experience",
        "location": "Umbria",
        "description": "Join local hunters and their dogs in search of prized truffles",
        "category": "Adventure",
        "rating": 4.8,
        "price": "$$$$",
        "duration": "4 hours",
        "availability": "Weekends"
    },
    {
        "activity_id": 19,
        "activity_name": "Amalfi Coast Cooking Class",
        "location": "Amalfi Coast",
        "description": "Learn to cook traditional Italian dishes with a local chef on the Amalfi Coast",
        "category": "Cooking Classes",
        "rating": 4.9,
        "price": "$$$",
        "duration": "3 hours",
        "availability": "Daily"
    },
    {
        "activity_id": 20,
        "activity_name": "Bike Tour of Rome",
        "location": "Rome",
        "description": "Discover Rome's historic landmarks and hidden gems on a guided bike tour",
        "category": "Adventure",
        "rating": 4.5,
        "price": "$$",
        "duration": "3 hours",
        "availability": "Daily"
    },
    {
        "activity_id": 21,
        "activity_name": "Lake Como Boat Tour",
        "location": "Lake Como",
        "description": "Enjoy a relaxing boat tour on the picturesque Lake Como",
        "category": "Boat Tours",
        "rating": 4.7,
        "price": "$$$",
        "duration": "2 hours",
        "availability": "Daily"
    },
    {
        "activity_id": 22,
        "activity_name": "Verona Arena Opera",
        "location": "Verona",
        "description": "Experience a world-class opera performance in the ancient Verona Arena",
        "category": "Art & Culture",
        "rating": 4.9,
        "price": "$$$$",
        "duration": "3 hours",
        "availability": "Specific dates"
    },
    {
        "activity_id": 23,
        "activity_name": "Matera Cave Tour",
        "location": "Matera",
        "description": "Explore the unique cave dwellings and ancient history of Matera",
        "category": "Sightseeing",
        "rating": 4.6,
        "price": "$$",
        "duration": "2 hours",
        "availability": "Daily"
    },
    {
        "activity_id": 24,
        "activity_name": "Milan Fashion Tour",
        "location": "Milan",
        "description": "Discover Milan's fashion district with a knowledgeable guide",
        "category": "Shopping",
        "rating": 4.8,
        "price": "$$$$",
        "duration": "3 hours",
        "availability": "Weekdays"
    },
    {
        "activity_id": 25,
        "activity_name": "Sicilian Cooking Class",
        "location": "Sicily",
        "description": "Learn to cook traditional Sicilian dishes with a local chef",
        "category": "Cooking Classes",
        "rating": 4.7,
        "price": "$$",
        "duration": "3 hours",
        "availability": "Daily"
    },
    {
        "activity_id": 26,
        "activity_name": "Assisi Walking Tour",
        "location": "Assisi",
        "description": "Explore the historic town of Assisi on a guided walking tour",
        "category": "Sightseeing",
        "rating": 4.5,
        "price": "$",
        "duration": "2 hours",
        "availability": "Daily"
    },
    {
        "activity_id": 27,
        "activity_name": "Etna Volcano Hike",
        "location": "Sicily",
        "description": "Hike up the slopes of Mount Etna, Europe's most active volcano",
        "category": "Adventure",
        "rating": 4.8,
        "price": "$$$",
        "duration": "Full day",
        "availability": "Daily"
    },
    {
        "activity_id": 28,
        "activity_name": "Rome Street Food Tour",
        "location": "Rome",
        "description": "Taste Rome's best street food on a guided tour through its neighborhoods",
        "category": "Food & Drink",
        "rating": 4.7,
        "price": "$$",
        "duration": "3 hours",
        "availability": "Daily"
    },
    {
        "activity_id": 29,
        "activity_name": "Florence Artisans Workshop",
        "location": "Florence",
        "description": "Visit local artisans and learn about traditional crafts in Florence",
        "category": "Workshops",
        "rating": 4.9,
        "price": "$$$",
        "duration": "2 hours",
        "availability": "Weekdays"
    },
    {
        "activity_id": 30,
        "activity_name": "Naples Underground Tour",
        "location": "Naples",
        "description": "Discover the hidden underground tunnels and catacombs of Naples",
        "category": "Sightseeing",
        "rating": 4.6,
        "price": "$$",
        "duration": "2 hours",
        "availability": "Daily"
    },
    {
        "activity_id": 31,
        "activity_name": "Torino Chocolate Tour",
        "location": "Turin",
        "description": "Indulge in a guided tour of Turin's best chocolateries and taste delicious chocolates",
        "category": "Food & Drink",
        "rating": 4.8,
        "price": "$$",
        "duration": "2 hours",
        "availability": "Weekends"
    },
    {
        "activity_id": 32,
        "activity_name": "Sardinia Beach Day",
        "location": "Sardinia",
        "description": "Relax on the beautiful beaches of Sardinia with sunbathing and swimming",
        "category": "Leisure",
        "rating": 4.7,
        "price": "$",
        "duration": "Full day",
        "availability": "Daily"
    },
    {
        "activity_id": 33,
        "activity_name": "Bologna Food Tour",
        "location": "Bologna",
        "description": "Experience the culinary delights of Bologna on a guided food tour",
        "category": "Food & Drink",
        "rating": 4.9,
        "price": "$$",
        "duration": "3 hours",
        "availability": "Daily"
    },
    {
        "activity_id": 34,
        "activity_name": "Trento Wine Tasting",
        "location": "Trento",
        "description": "Enjoy wine tasting in the beautiful region of Trento",
        "category": "Food & Drink",
        "rating": 4.6,
        "price": "$$$",
        "duration": "3 hours",
        "availability": "Weekends"
    },
    {
        "activity_id": 35,
        "activity_name": "Ravenna Mosaics Tour",
        "location": "Ravenna",
        "description": "Explore the stunning mosaics of Ravenna with a knowledgeable guide",
        "category": "Art & Culture",
        "rating": 4.8,
        "price": "$$",
        "duration": "2 hours",
        "availability": "Daily"
    },
    {
        "activity_id": 36,
        "activity_name": "Sardinia Snorkeling Adventure",
        "location": "Sardinia",
        "description": "Discover the underwater world of Sardinia with a guided snorkeling tour",
        "category": "Water Tours",
        "rating": 4.7,
        "price": "$$$",
        "duration": "Half day",
        "availability": "Daily"
    },
    {
        "activity_id": 37,
        "activity_name": "Rome Ghost Tour",
        "location": "Rome",
        "description": "Experience the spooky side of Rome on a guided ghost tour",
        "category": "Adventure",
        "rating": 4.5,
        "price": "$$",
        "duration": "2 hours",
        "availability": "Evenings"
    },
    {
        "activity_id": 38,
        "activity_name": "Cinque Terre Boat Tour",
        "location": "Cinque Terre",
        "description": "Enjoy a scenic boat tour along the beautiful Cinque Terre coast",
        "category": "Boat Tours",
        "rating": 4.8,
        "price": "$$$",
        "duration": "Half day",
        "availability": "Daily"
    },
    {
        "activity_id": 39,
        "activity_name": "Perugia Chocolate Making Class",
        "location": "Perugia",
        "description": "Learn the art of chocolate making in the heart of Perugia",
        "category": "Cooking Classes",
        "rating": 4.9,
        "price": "$$$",
        "duration": "3 hours",
        "availability": "Weekends"
    },
    {
        "activity_id": 40,
        "activity_name": "Puglia Olive Oil Tasting",
        "location": "Puglia",
        "description": "Taste and learn about the finest olive oils in Puglia",
        "category": "Food & Drink",
        "rating": 4.7,
        "price": "$$",
        "duration": "2 hours",
        "availability": "Daily"
    },
    {
        "activity_id": 41,
        "activity_name": "Venice Ghost & Legends Tour",
        "location": "Venice",
        "description": "Explore the spooky and mysterious side of Venice on a ghost tour",
        "category": "Adventure",
        "rating": 4.6,
        "price": "$$",
        "duration": "2 hours",
        "availability": "Evenings"
    },
    {
        "activity_id": 42,
        "activity_name": "Florence Duomo Climb",
        "location": "Florence",
        "description": "Climb to the top of Florence's Duomo for breathtaking views",
        "category": "Sightseeing",
        "rating": 4.8,
        "price": "$$",
        "duration": "1 hour",
        "availability": "Daily"
    },
    {
        "activity_id": 43,
        "activity_name": "Vatican Night Tour",
        "location": "Rome",
        "description": "Discover the Vatican Museums after hours on an exclusive night tour",
        "category": "Art & Culture",
        "rating": 4.9,
        "price": "$$$",
        "duration": "3 hours",
        "availability": "Specific dates"
    },
    {
        "activity_id": 44,
        "activity_name": "Lake Garda Wine Tasting",
        "location": "Lake Garda",
        "description": "Savor the flavors of Lake Garda with a guided wine tasting experience",
        "category": "Food & Drink",
        "rating": 4.7,
        "price": "$$$",
        "duration": "2 hours",
        "availability": "Weekends"
    },
    {
        "activity_id": 45,
        "activity_name": "Sicilian Puppet Show",
        "location": "Sicily",
        "description": "Experience traditional Sicilian puppetry with a lively puppet show",
        "category": "Entertainment",
        "rating": 4.6,
        "price": "$",
        "duration": "1 hour",
        "availability": "Evenings"
    },
    {
        "activity_id": 46,
        "activity_name": "Alberobello Trullo Tour",
        "location": "Alberobello",
        "description": "Explore the unique trulli houses of Alberobello, a UNESCO World Heritage site",
        "category": "Sightseeing",
        "rating": 4.8,
        "price": "$$",
        "duration": "2 hours",
        "availability": "Daily"
    },
    {
        "activity_id": 47,
        "activity_name": "Venice Grand Canal Cruise",
        "location": "Venice",
        "description": "Cruise along Venice's iconic Grand Canal and admire the city's landmarks",
        "category": "Boat Tours",
        "rating": 4.9,
        "price": "$$$",
        "duration": "1 hour",
        "availability": "Daily"
    },
    {
        "activity_id": 48,
        "activity_name": "Naples Archaeological Museum",
        "location": "Naples",
        "description": "Explore the rich history of Naples at the Archaeological Museum",
        "category": "Museums",
        "rating": 4.7,
        "price": "$$",
        "duration": "2 hours",
        "availability": "Daily"
    },
    {
        "activity_id": 49,
        "activity_name": "Lake Maggiore Boat Tour",
        "location": "Lake Maggiore",
        "description": "Embark on a scenic boat tour of Lake Maggiore and its charming islands",
        "category": "Boat Tours",
        "rating": 4.6,
        "price": "$$$",
        "duration": "3 hours",
        "availability": "Daily"
    },
    {
        "activity_id": 50,
        "activity_name": "Bari Street Food Tour",
        "location": "Bari",
        "description": "Taste the diverse street food offerings of Bari on a guided culinary tour",
        "category": "Food & Drink",
        "rating": 4.8,
        "price": "$$",
        "duration": "2 hours",
        "availability": "Daily"
    },
    {
        "activity_id": 51,
        "activity_name": "Verona Juliet's House",
        "location": "Verona",
        "description": "Visit the legendary Juliet's House in Verona and see the famous balcony",
        "category": "Sightseeing",
        "rating": 4.7,
        "price": "$",
        "duration": "1 hour",
        "availability": "Daily"
    },
    {
        "activity_id": 52,
        "activity_name": "Turin Shroud Museum",
        "location": "Turin",
        "description": "Explore the mysteries of the Turin Shroud at the Shroud Museum",
        "category": "Museums",
        "rating": 4.5,
        "price": "$$",
        "duration": "2 hours",
        "availability": "Weekdays"
    },
    {
        "activity_id": 53,
        "activity_name": "Lake Como Villa Tour",
        "location": "Lake Como",
        "description": "Tour the elegant villas and gardens along the shores of Lake Como",
        "category": "Sightseeing",
        "rating": 4.8,
        "price": "$$$",
        "duration": "3 hours",
        "availability": "Weekends"
    },
    {
        "activity_id": 54,
        "activity_name": "Genoa Aquarium",
        "location": "Genoa",
        "description": "Discover the wonders of the sea at Europe's largest aquarium in Genoa",
        "category": "Family-Friendly",
        "rating": 4.6,
        "price": "$$",
        "duration": "2 hours",
        "availability": "Daily"
    },
    {
        "activity_id": 55,
        "activity_name": "Bologna Towers Climb",
        "location": "Bologna",
        "description": "Climb the medieval towers of Bologna for panoramic views of the city",
        "category": "Sightseeing",
        "rating": 4.7,
        "price": "$$",
        "duration": "1 hour",
        "availability": "Weekends"
    },
    {
        "activity_id": 56,
        "activity_name": "Padua Botanical Garden",
        "location": "Padua",
        "description": "Stroll through the oldest botanical garden in the world in Padua",
        "category": "Gardens",
        "rating": 4.9,
        "price": "$",
        "duration": "1 hour",
        "availability": "Daily"
    },
    {
        "activity_id": 57,
        "activity_name": "Ravenna Dante's Tomb",
        "location": "Ravenna",
        "description": "Pay homage to the great poet Dante Alighieri at his tomb in Ravenna",
        "category": "Sightseeing",
        "rating": 4.5,
        "price": "$",
        "duration": "1 hour",
        "availability": "Weekdays"
    },
    {
        "activity_id": 58,
        "activity_name": "Milan Navigli District Walk",
        "location": "Milan",
        "description": "Explore the trendy Navigli district of Milan with its canals and cafes",
        "category": "Sightseeing",
        "rating": 4.8,
        "price": "$$",
        "duration": "2 hours",
        "availability": "Daily"
    },
    {
        "activity_id": 59,
        "activity_name": "Bari Cathedral",
        "location": "Bari",
        "description": "Admire the stunning architecture of Bari Cathedral in the heart of the old town",
        "category": "Sightseeing",
        "rating": 4.6,
        "price": "$",
        "duration": "1 hour",
        "availability": "Weekdays"
    },
    {
        "activity_id": 60,
        "activity_name": "Taormina Greek Theatre",
        "location": "Taormina",
        "description": "Visit the ancient Greek Theatre of Taormina with its breathtaking views",
        "category": "Sightseeing",
        "rating": 4.7,
        "price": "$",
        "duration": "1 hour",
        "availability": "Daily"
    },
    {
        "activity_id": 61,
        "activity_name": "Palermo Street Market",
        "location": "Palermo",
        "description": "Experience the vibrant colors and flavors of Palermo's street markets",
        "category": "Shopping",
        "rating": 4.8,
        "price": "$",
        "duration": "2 hours",
        "availability": "Weekends"
    },
    {
        "activity_id": 62,
        "activity_name": "Catania Fish Market Tour",
        "location": "Catania",
        "description": "Discover the lively fish market of Catania and taste fresh seafood delicacies",
        "category": "Food & Drink",
        "rating": 4.7,
        "price": "$$",
        "duration": "2 hours",
        "availability": "Weekdays"
    },
    {
        "activity_id": 63,
        "activity_name": "Bologna Bookshops Walk",
        "location": "Bologna",
        "description": "Browse the charming bookshops and libraries of Bologna's historic center",
        "category": "Shopping",
        "rating": 4.6,
        "price": "$",
        "duration": "1 hour",
        "availability": "Daily"
    },
    {
        "activity_id": 64,
        "activity_name": "Milan Design District Tour",
        "location": "Milan",
        "description": "Explore Milan's design district and discover cutting-edge architecture and design",
        "category": "Art & Culture",
        "rating": 4.9,
        "price": "$$$",
        "duration": "2 hours",
        "availability": "Weekdays"
    },
    {
        "activity_id": 65,
        "activity_name": "Bergamo Città Alta Walk",
        "location": "Bergamo",
        "description": "Take a leisurely walk through the charming medieval streets of Bergamo's Upper Town",
        "category": "Sightseeing",
        "rating": 4.7,
        "price": "$",
        "duration": "2 hours",
        "availability": "Daily"
    },
    {
        "activity_id": 66,
        "activity_name": "Parma Cheese Factory Tour",
        "location": "Parma",
        "description": "Learn about the production of Parmigiano Reggiano cheese at a local factory",
        "category": "Food & Drink",
        "rating": 4.8,
        "price": "",
        "duration": "2 hours",
        "availability": "Weekdays"
        },
        {
        "activity_id": 67,
        "activity_name": "Piedmont Truffle Fair",
        "location": "Piedmont",
        "description": "Experience the excitement of the truffle fair in Piedmont and taste gourmet truffle dishes",
        "category": "Food & Drink",
        "rating": 4.9,
        "price": "$$$",
        "duration": "1 day",
        "availability": "Specific dates"
        },
        {
        "activity_id": 68,
        "activity_name": "Lucca Cycling Tour",
        "location": "Lucca",
        "description": "Explore the charming streets and medieval walls of Lucca by bicycle",
        "category": "Adventure",
        "rating": 4.6,
        "price": "",
        "duration": "3 hours",
        "availability": "Weekends"
        },
        {
        "activity_id": 69,
        "activity_name": "Naples Street Art Tour",
        "location": "Naples",
        "description": "Discover the vibrant street art scene of Naples on a guided walking tour",
        "category": "Art & Culture",
        "rating": 4.7,
        "price": "$",
        "duration": "2 hours",
        "availability": "Weekdays"
        },
        {
        "activity_id": 70,
        "activity_name": "Orvieto Underground Tour",
        "location": "Orvieto",
        "description": "Explore the underground tunnels and caves beneath the historic city of Orvieto",
        "category": "Adventure",
        "rating": 4.5,
        "price": "",
        "duration": "1 hour",
        "availability": "Daily"
        },
        {
        "activity_id": 71,
        "activity_name": "Portofino Boat Tour",
        "location": "Portofino",
        "description": "Cruise along the Ligurian coast and admire the scenic beauty of Portofino",
        "category": "Boat Tours",
        "rating": 4.8,
        "price": "$$$",
        "duration": "Half day",
        "availability": "Daily"
        },
        {
        "activity_id": 72,
        "activity_name": "Pompeii Archaeological Site",
        "location": "Pompeii",
        "description": "Explore the ancient ruins of Pompeii and uncover the city frozen in time",
        "category": "Sightseeing",
        "rating": 4.9,
        "price": "$",
        "duration": "Half day",
        "availability": "Daily"
        },
        {
        "activity_id": 73,
        "activity_name": "Syracuse Greek Theatre",
        "location": "Syracuse",
        "description": "Visit the well-preserved Greek Theatre of Syracuse and marvel at its ancient grandeur",
        "category": "Sightseeing",
        "rating": 4.7,
        "price": "$",
        "duration": "1 hour",
        "availability": "Daily"
        },
        {
        "activity_id": 74,
        "activity_name": "Cagliari Segway Tour",
        "location": "Cagliari",
        "description": "Glide through the streets of Cagliari on a fun and informative Segway tour",
        "category": "Adventure",
        "rating": 4.6,
        "price": "",
        "duration": "2 hours",
        "availability": "Weekends"
        },
        {
        "activity_id": 75,
        "activity_name": "Pisa Walking Tour",
        "location": "Pisa",
        "description": "Discover the landmarks of Pisa on a guided walking tour of the city",
        "category": "Sightseeing",
        "rating": 4.8,
        "price": "$",
        "duration": "2 hours",
        "availability": "Daily"
        },
        {
        "activity_id": 76,
        "activity_name": "Bologna Gelato Making Class",
        "location": "Bologna",
        "description": "Learn the art of making authentic Italian gelato from a master gelato maker",
        "category": "Cooking Classes",
        "rating": 4.9,
        "price": "$$",
        "duration": "2 hours",
        "availability": "Weekdays"
        },
        {
        "activity_id": 77,
        "activity_name": "Rimini Beach Day",
        "location": "Rimini",
        "description": "Relax on the sandy beaches of Rimini and soak up the Mediterranean sun",
        "category": "Leisure",
        "rating": 4.7,
        "price": "$",
        "duration": "Full day",
        "availability": "Daily"
        },
        {
            "activity_id": 78,
            "activity_name": "Modena Balsamic Vinegar Tour",
            "location": "Modena",
            "description": "Tour a traditional balsamic vinegar factory in Modena and taste aged balsamic vinegar",
            "category": "Food & Drink",
            "rating": 4.8,
            "price": "$$",
            "duration": "2 hours",
            "availability": "Weekdays"
        },
        {
            "activity_id": 79,
            "activity_name": "Pistoia Hot Air Balloon Ride",
            "location": "Pistoia",
            "description": "Soar above the picturesque landscape of Tuscany on a hot air balloon ride",
            "category": "Adventure",
            "rating": 4.9,
            "price": "$$$",
            "duration": "2 hours",
            "availability": "Weekends"
        },
        {
            "activity_id": 80,
            "activity_name": "Livorno Seafood Tasting",
            "location": "Livorno",
            "description": "Sample fresh seafood delicacies at the lively seafood markets of Livorno",
            "category": "Food & Drink",
            "rating": 4.7,
            "price": "$$",
            "duration": "2 hours",
            "availability": "Weekends"
        },
        {
            "activity_id": 81,
            "activity_name": "Verona Wine Tasting",
            "location": "Verona",
            "description": "Enjoy wine tasting in the renowned wine regions surrounding Verona",
            "category": "Food & Drink",
            "rating": 4.8,
            "price": "$$$",
            "duration": "3 hours",
            "availability": "Daily"
        },
        {
            "activity_id": 82,
            "activity_name": "Turin Cinema Museum",
            "location": "Turin",
            "description": "Explore the history of cinema at the fascinating Cinema Museum in Turin",
            "category": "Museums",
            "rating": 4.6,
            "price": "$",
            "duration": "2 hours",
            "availability": "Weekdays"
        },
        {
            "activity_id": 83,
            "activity_name": "Cesenatico Fisherman's Museum",
            "location": "Cesenatico",
            "description": "Learn about the maritime heritage of Cesenatico at its Fisherman's Museum",
            "category": "Museums",
            "rating": 4.7,
            "price": "$",
            "duration": "1 hour",
            "availability": "Daily"
        },
        {
            "activity_id": 84,
            "activity_name": "Parco Nazionale delle Cinque Terre Hike",
            "location": "Cinque Terre",
            "description": "Embark on a scenic hike through the rugged terrain of Cinque Terre National Park",
            "category": "Adventure",
            "rating": 4.9,
            "price": "$$",
            "duration": "Full day",
            "availability": "Daily"
        },
        {
            "activity_id": 85,
            "activity_name": "San Gimignano Wine Tour",
            "location": "San Gimignano",
            "description": "Discover the medieval charm of San Gimignano while sampling its renowned wines",
            "category": "Food & Drink",
            "rating": 4.8,
            "price": "$$$",
            "duration": "4 hours",
            "availability": "Weekends"
        },
        {
            "activity_id": 86,
            "activity_name": "Ravenna Beach Day",
            "location": "Ravenna",
            "description": "Relax on the sandy beaches of Ravenna and enjoy the tranquil Adriatic Sea",
            "category": "Leisure",
            "rating": 4.7,
            "price": "$",
            "duration": "Full day",
            "availability": "Daily"
        },
        {
            "activity_id": 87,
            "activity_name": "Agrigento Valley of the Temples",
            "location": "Agrigento",
            "description": "Explore the well-preserved ancient Greek temples in the Valley of the Temples",
            "category": "Sightseeing",
            "rating": 4.9,
            "price": "$$",
            "duration": "Half day",
            "availability": "Daily"
        },
        {
            "activity_id": 88,
            "activity_name": "Montepulciano Wine Tasting",
            "location": "Montepulciano",
            "description": "Savor the bold flavors of Montepulciano's renowned Vino Nobile wines",
            "category": "Food & Drink",
            "rating": 4.8,
            "price": "$$$",
            "duration": "3 hours",
            "availability": "Weekends"
        },
        {
            "activity_id": 89,
            "activity_name": "Aosta Valley Skiing",
            "location": "Aosta Valley",
            "description": "Hit the slopes and enjoy world-class skiing in the scenic Aosta Valley",
            "category": "Adventure",
            "rating": 4.9,
            "price": "$$$",
            "duration": "Full day",
            "availability": "Winter season"
        },
        {
            "activity_id": 90,
            "activity_name": "Lipari Island Boat Tour",
            "location": "Lipari",
            "description": "Sail around the beautiful Aeolian Islands and explore the stunning coastline of Lipari",
            "category": "Boat Tours",
            "rating": 4.7,
            "price": "$$$",
            "duration": "Full day",
            "availability": "Daily"
        },
        {
            "activity_id": 91,
            "activity_name": "Bologna Historic Center Walking Tour",
            "location": "Bologna",
            "description": "Stroll through the historic center of Bologna and admire its medieval architecture",
            "category": "Sightseeing",
            "rating": 4.8,
            "price": "$",
            "duration": "2 hours",
            "availability": "Daily"
        },
        {
            "activity_id": 92,
            "activity_name": "Lecce Baroque Walking Tour",
            "location": "Lecce",
            "description": "Discover the ornate beauty of Lecce's Baroque architecture on a guided walking tour",
            "category": "Sightseeing",
            "rating": 4.7,
            "price": "$$",
            "duration": "2 hours",
            "availability": "Daily"
        }

]